Workbook

Sheet Assumptions
A1: AdSniper — operating-cost assumptions (per dedicated customer instance, monthly USD)
A2: MODELED, not yet reconciled against a real invoice. Provider figures are the Gate-2 pilot's job; every rate below is a documented baseline or public list price. Blue = input you can change; yellow = key lever.
A4: Cost line | B4: Base | C4: High | D4: Basis / source
A5: Ads provider — Meta+Google, per tracked brand | B5: 4.5 | C5: 9 | D5: Modeled from README baseline ($60–120/mo at 100-ad caps, 9 brands, 3 libraries); scaled to 2 libraries. Reconcile in the Gate-2 pilot.
A6: Organic provider — X+LinkedIn posts, per tracked brand | B6: 0.5 | C6: 1.5 | D6: README: X ~$3–6/mo, LinkedIn ~$2–4/mo across the brand set. Secondary module.
A7: Apify subscription floor (dedicated token, Starter) | B7: 19 | C7: 19 | D7: apify.com/pricing — Starter $19/mo incl. $19 usage credit; usage above draws overage.
A8: Hosting — Railway app service + Postgres + volume | B8: 16 | C8: 30 | D8: railway.com/pricing usage rates: RAM $0.00000386/GB/s, vCPU $0.00000772/vCPU/s. Small always-on Node + Postgres.
A9: Storage — Cloudflare R2 (per instance) | B9: 0.25 | C9: 2 | D9: R2 $0.015/GB-mo, egress free, 10 GB free tier. ~0.5–1.5 GB/mo media growth.
A10: AI briefings — Anthropic (per instance) | B10: 2 | C10: 5 | D10: Claude Sonnet 5 $2/$10 per MTok. Daily+weekly briefs are small; optional (facts-only fallback if unset).
A11: Email — Resend (per instance) | B11: 0 | C11: 1 | D11: resend.com/pricing free 3,000/mo covers login magic links; one account serves the fleet.
A12: Support — internal operator effort (per instance) | B12: 25 | C12: 75 | D12: ESTIMATE, internal labor not cash. Onboarding + ongoing support. Confirm with the first real onboarding (Gate 5).
A14: USD → SAR peg | B14: 3.75

Sheet CostModel
A1: Annual operating cost per instance — 3 / 5 / 9 tracked brands (self + competitors), Base vs High usage
C2: 3-brand | D2: 3-brand | E2: 5-brand | F2: 5-brand | G2: 9-brand | H2: 9-brand
A3: Cost line (monthly USD) | C3: Base | D3: High | E3: Base | F3: High | G3: Base | H3: High
A4: Tracked brands (self + competitors) | C4: 3 | D4: 3 | E4: 5 | F4: 5 | G4: 9 | H4: 9
A5: Apify (provider scraping) — MAX(floor, ads+organic usage) | C5: =MAX(Assumptions!$B$7, (Assumptions!$B$5+Assumptions!$B$6)*C$4) -> 19 | D5: =MAX(Assumptions!$C$7, (Assumptions!$C$5+Assumptions!$C$6)*D$4) -> 31.5 | E5: =MAX(Assumptions!$B$7, (Assumptions!$B$5+Assumptions!$B$6)*E$4) -> 25 | F5: =MAX(Assumptions!$C$7, (Assumptions!$C$5+Assumptions!$C$6)*F$4) -> 52.5 | G5: =MAX(Assumptions!$B$7, (Assumptions!$B$5+Assumptions!$B$6)*G$4) -> 45 | H5: =MAX(Assumptions!$C$7, (Assumptions!$C$5+Assumptions!$C$6)*H$4) -> 94.5
A6: Railway hosting (app + Postgres) | C6: =Assumptions!$B$8 -> 16 | D6: =Assumptions!$C$8 -> 30 | E6: =Assumptions!$B$8 -> 16 | F6: =Assumptions!$C$8 -> 30 | G6: =Assumptions!$B$8 -> 16 | H6: =Assumptions!$C$8 -> 30
A7: Cloudflare R2 storage | C7: =Assumptions!$B$9 -> 0.25 | D7: =Assumptions!$C$9 -> 2 | E7: =Assumptions!$B$9 -> 0.25 | F7: =Assumptions!$C$9 -> 2 | G7: =Assumptions!$B$9 -> 0.25 | H7: =Assumptions!$C$9 -> 2
A8: AI briefings (Anthropic) | C8: =Assumptions!$B$10 -> 2 | D8: =Assumptions!$C$10 -> 5 | E8: =Assumptions!$B$10 -> 2 | F8: =Assumptions!$C$10 -> 5 | G8: =Assumptions!$B$10 -> 2 | H8: =Assumptions!$C$10 -> 5
A9: Email (Resend) | C9: =Assumptions!$B$11 -> 0 | D9: =Assumptions!$C$11 -> 1 | E9: =Assumptions!$B$11 -> 0 | F9: =Assumptions!$C$11 -> 1 | G9: =Assumptions!$B$11 -> 0 | H9: =Assumptions!$C$11 -> 1
A10: Support — internal operator effort | C10: =Assumptions!$B$12 -> 25 | D10: =Assumptions!$C$12 -> 75 | E10: =Assumptions!$B$12 -> 25 | F10: =Assumptions!$C$12 -> 75 | G10: =Assumptions!$B$12 -> 25 | H10: =Assumptions!$C$12 -> 75
A11: Monthly total (fully loaded) | C11: =SUM(C5:C10) -> 62.25 | D11: =SUM(D5:D10) -> 144.5 | E11: =SUM(E5:E10) -> 68.25 | F11: =SUM(F5:F10) -> 165.5 | G11: =SUM(G5:G10) -> 88.25 | H11: =SUM(H5:H10) -> 207.5
A12: ANNUAL total (fully loaded) | C12: =C11*12 -> 747 | D12: =D11*12 -> 1734 | E12: =E11*12 -> 819 | F12: =F11*12 -> 1986 | G12: =G11*12 -> 1059 | H12: =H11*12 -> 2490
A13: ANNUAL cash cost (excl. internal support labor) | C13: =(C11-C10)*12 -> 447 | D13: =(D11-D10)*12 -> 834 | E13: =(E11-E10)*12 -> 519 | F13: =(F11-F10)*12 -> 1086 | G13: =(G11-G10)*12 -> 759 | H13: =(H11-H10)*12 -> 1590
A14: ANNUAL total in SAR (fully loaded) | C14: =C12*Assumptions!$B$14 -> 2801.25 | D14: =D12*Assumptions!$B$14 -> 6502.5 | E14: =E12*Assumptions!$B$14 -> 3071.25 | F14: =F12*Assumptions!$B$14 -> 7447.5 | G14: =G12*Assumptions!$B$14 -> 3971.25 | H14: =H12*Assumptions!$B$14 -> 9337.5
A16: Read: provider (Apify) and internal support dominate; hosting/storage/AI/email are small and near-fixed. The cost delta between 3 and 9 brands is modest — so pricing should NOT be cost-plus per brand (see Pricing).

Sheet Pricing
A1: Pricing recommendation — annual per dedicated instance (RECOMMENDATION; needs operator sign-off + beta validation)
A2: Cost is the floor, not the anchor. Shared-seat tools ($9–159/mo ≈ $108–1,908/yr) are NOT comparable to a dedicated, isolated, Arabic-first instance with an executive briefing. Price on value; the model below shows margin is not the constraint.
A4: Scenario | B4: Annual USD | C4: Annual SAR | D4: Fully-loaded COGS (9-brand High) | E4: Gross margin | F4: Notes
A5: Standard — List (up to 5 competitors) | B5: 25600 | C5: =B5*Assumptions!$B$14 -> 96000 | D5: =CostModel!$H$12 -> 2490 | E5: =(B5-D5)/B5 -> 0.90273437 | F5: Anchor. SAR 96,000. All features, standard isolation.
A6: Standard — Target | B6: 20000 | C6: =B6*Assumptions!$B$14 -> 75000 | D6: =CostModel!$H$12 -> 2490 | E6: =(B6-D6)/B6 -> 0.8755 | F6: SAR 75,000. Expected close for a mid-size bank.
A7: Standard — Floor (approval required) | B7: 14667 | C7: =B7*Assumptions!$B$14 -> 55001.25 | D7: =CostModel!$H$12 -> 2490 | E7: =(B7-D7)/B7 -> 0.83023113 | F7: SAR 55,000. Below this needs exec sign-off.
A8: Enterprise exception (up to 9 + separate Cloudflare acct) | B8: 40000 | C8: =B8*Assumptions!$B$14 -> 150000 | D8: =CostModel!$H$12 -> 2490 | E8: =(B8-D8)/B8 -> 0.93775 | F8: SAR 150,000. Strict-compliance buyers only.
A9: Beta / design partner (year 1, first 2–3) | B9: 8000 | C9: =B9*Assumptions!$B$14 -> 30000 | D9: =CostModel!$H$12 -> 2490 | E9: =(B9-D9)/B9 -> 0.68875 | F9: SAR 30,000 (~60% off) for a reference + feedback + case study.
A11: Provider ceiling per plan (MONTHLY_COST_CEILING_ADS_USD): Standard $60 · Enterprise $120. The ceiling is the margin guardrail.
A12: Discount authority: Sales → Target freely · Floor needs head-of-function · below Floor needs exec. Record the final decision in docs/DECISIONS.md.
